ShiptheoryPython/__init__.py
ShiptheoryPython/Http/AccessToken.py
ShiptheoryPython/Http/Api.py
ShiptheoryPython/Http/ResponseObject.py
ShiptheoryPython/Http/ShiptheoryClient.py
ShiptheoryPython/Http/__init__.py
ShiptheoryPython/Objects/Address.py
ShiptheoryPython/Objects/ClientObject.py
ShiptheoryPython/Objects/ListShipmentQuery.py
ShiptheoryPython/Objects/Package.py
ShiptheoryPython/Objects/PackageQuery.py
ShiptheoryPython/Objects/Product.py
ShiptheoryPython/Objects/ProductQuery.py
ShiptheoryPython/Objects/QueryObject.py
ShiptheoryPython/Objects/Recipient.py
ShiptheoryPython/Objects/ReturnLabel.py
ShiptheoryPython/Objects/SearchShipmentQuery.py
ShiptheoryPython/Objects/Sender.py
ShiptheoryPython/Objects/SharedProduct.py
ShiptheoryPython/Objects/Shipment.py
ShiptheoryPython/Objects/ShipmentDetail.py
ShiptheoryPython/Objects/ShipmentProduct.py
ShiptheoryPython/Objects/ShipmentQuery.py
ShiptheoryPython/Objects/TaxNumber.py
ShiptheoryPython/Objects/__init__.py
shiptheory_python-1.0.0.dist-info/LICENSE
shiptheory_python-1.0.0.dist-info/METADATA
shiptheory_python-1.0.0.dist-info/WHEEL
shiptheory_python-1.0.0.dist-info/top_level.txt
shiptheory_python-1.0.0.dist-info/RECORD
