Metadata-Version: 2.1
Name: shiptheory-python
Version: 1.0.0
Summary: Client to communicate with the Shiptheory API
Author-email: Dan Rogers <dan.rogers@shiptheory.com>
License: MIT License        
Project-URL: Homepage, https://github.com/DanRVP/shiptheory-python
Keywords: api,shiptheory,api client
Classifier: License :: OSI Approved :: MIT License
Classifier: Programming Language :: Python
Classifier: Programming Language :: Python :: 3
Requires-Python: >=3.10
License-File: LICENSE
